pycons3rt3/__init__.py
pycons3rt3/aliasip.py
pycons3rt3/ansiblevault.py
pycons3rt3/asset.py
pycons3rt3/aws_metadata.py
pycons3rt3/awsutil.py
pycons3rt3/azcomputeutil.py
pycons3rt3/azure_metadata.py
pycons3rt3/bash.py
pycons3rt3/cloud.py
pycons3rt3/cloudwatchutil.py
pycons3rt3/cons3rt.py
pycons3rt3/cons3rtapi.py
pycons3rt3/cons3rtcli.py
pycons3rt3/cons3rtclient.py
pycons3rt3/cons3rtconfig.py
pycons3rt3/cons3rtdefaults.py
pycons3rt3/cons3rtenums.py
pycons3rt3/cons3rtinfra.py
pycons3rt3/cons3rtwaiters.py
pycons3rt3/deployment.py
pycons3rt3/dyndict.py
pycons3rt3/ec2util.py
pycons3rt3/elbv2util.py
pycons3rt3/exceptions.py
pycons3rt3/hostmigration.py
pycons3rt3/httpclient.py
pycons3rt3/iamutil.py
pycons3rt3/images.py
pycons3rt3/kmsutil.py
pycons3rt3/logify.py
pycons3rt3/mailchimp.py
pycons3rt3/network.py
pycons3rt3/nexus.py
pycons3rt3/offline.py
pycons3rt3/openssl.py
pycons3rt3/ostemplates.py
pycons3rt3/osutil.py
pycons3rt3/password.py
pycons3rt3/pycons3rtlibs.py
pycons3rt3/pygit.py
pycons3rt3/pyjavakeys.py
pycons3rt3/rdsutil.py
pycons3rt3/remoteaccesscontoller.py
pycons3rt3/reports.py
pycons3rt3/route53util.py
pycons3rt3/s3organizer.py
pycons3rt3/s3util.py
pycons3rt3/scenario.py
pycons3rt3/service_runner.py
pycons3rt3/slack.py
pycons3rt3/ssh.py
pycons3rt3/stsutil.py
pycons3rt3/teams.py
pycons3rt3/test_exceptions.py
pycons3rt3/windows.py
pycons3rt3-0.0.30.dist-info/licenses/LICENSE
pycons3rt3-0.0.30.dist-info/METADATA
pycons3rt3-0.0.30.dist-info/WHEEL
pycons3rt3-0.0.30.dist-info/entry_points.txt
pycons3rt3-0.0.30.dist-info/top_level.txt
pycons3rt3-0.0.30.dist-info/RECORD
