Metadata-Version: 2.4
Name: pycons3rt3
Version: 0.0.30
Summary: A python3 library for CONS3RT assets and API calls
Author-email: Joe Yennaco <joe.yennaco@jackpinetech.com>, Todd Fisher <todd.fisher@jackpinetech.com>, John Paulo <john.paulo@jackpinetech.com>
License: GNU GENERAL PUBLIC LICENSE
Project-URL: Homepage, https://pypi.org/project/pycons3rt3/
Project-URL: Documentation, https://github.com/cons3rt/pycons3rt3/blob/master/README.md
Project-URL: Repository, https://github.com/cons3rt/pycons3rt3.git
Project-URL: Issues, https://github.com/cons3rt/pycons3rt3/issues
Project-URL: Changelog, https://github.com/cons3rt/pycons3rt3/blob/master/CHANGELOG.md
Keywords: cons3rt,pycons3rt,pycons3rt3,assets,arcus,nimbuscore,97helix
Classifier: Development Status :: 5 - Production/Stable
Classifier: Programming Language :: Python :: 3
Requires-Python: >=3.6
License-File: LICENSE
Requires-Dist: boto3
Requires-Dist: botocore
Requires-Dist: cryptography>=42.0.5
Requires-Dist: jinja2>=3.1.3
Requires-Dist: paramiko>=3.4.0
Requires-Dist: progressbar2
Requires-Dist: pyyaml
Requires-Dist: requests>=2.31.0
Requires-Dist: requests[security]>=2.31.0
Requires-Dist: requests-toolbelt
Requires-Dist: s3transfer
Requires-Dist: scp
Requires-Dist: urllib3
Dynamic: license-file
